pheme/__init__.py
pheme/authentication.py
pheme/datalink.py
pheme/errors.py
pheme/parameter.py
pheme/parser/__init__.py
pheme/parser/xml.py
pheme/renderer.py
pheme/settings.py
pheme/storage.py
pheme/templatetags/__init__.py
pheme/templatetags/charts/__init__.py
pheme/templatetags/charts/h_bar.py
pheme/templatetags/charts/pie.py
pheme/templatetags/charts/treemap.py
pheme/templatetags/dynamic_template.py
pheme/templatetags/readable_timeformat.py
pheme/transformation/__init__.py
pheme/transformation/scanreport/__init__.py
pheme/transformation/scanreport/gvmd.py
pheme/transformation/scanreport/model.py
pheme/transformation/scanreport/renderer.py
pheme/urls.py
pheme/version/__init__.py
pheme/version/__version__.py
pheme/views.py
pheme/wsgi.py
pheme-21.11.1.dist-info/METADATA
pheme-21.11.1.dist-info/WHEEL
pheme-21.11.1.dist-info/licenses/LICENSE
pheme-21.11.1.dist-info/RECORD
