Metadata-Version: 2.4
Name: pheme
Version: 21.11.1
Summary: report-generation-service
License: AGPL-3.0-or-later
License-File: LICENSE
Author: Greenbone AG
Author-email: info@greenbone.net
Requires-Python: >=3.9,<4.0
Classifier: Development Status :: 4 - Beta
Classifier: Environment :: Web Environment
Classifier: Intended Audience :: Developers
Classifier: License :: OSI Approved :: GNU Affero General Public License v3 or later (AGPLv3+)
Classifier: Operating System :: OS Independent
Classifier: Programming Language :: Python :: 3
Classifier: Programming Language :: Python :: 3.9
Classifier: Programming Language :: Python :: 3.10
Classifier: Programming Language :: Python :: 3.11
Classifier: Programming Language :: Python :: 3.12
Classifier: Programming Language :: Python :: 3.13
Classifier: Programming Language :: Python :: 3.14
Classifier: Topic :: Internet :: WWW/HTTP :: WSGI :: Server
Provides-Extra: tracking
Requires-Dist: coreapi (>=2.3.3,<3.0.0)
Requires-Dist: django (==4.2.26)
Requires-Dist: djangorestframework (==3.16.1)
Requires-Dist: pyyaml (>=5.3.1,<7.0.0)
Requires-Dist: rope (>=0.17,<1.15)
Requires-Dist: sentry-sdk (>=1.1,<3.0) ; extra == "tracking"
Requires-Dist: uritemplate (>=3.0.1,<5.0.0)
Requires-Dist: weasyprint (>=62)
Requires-Dist: xmltodict (>=0.12,<1.1)
